[
  {
    "id": "1",
    "videoId": "4p_bEo7bj0g",
    "title": "Resep Healthy Snacking - Wedang Rempah Banyumasan",
    "thumbnail": "https://i.ytimg.com/vi/4p_bEo7bj0g/mqdefault.jpg",
    "duration": "00:55",
    "position": 1
  },
  {
    "id": "2", 
    "videoId": "Pv87WbHpcj0",
    "title": "Resep Healthy Snacking - Mango Sago Shake",
    "thumbnail": "https://i.ytimg.com/vi/Pv87WbHpcj0/mqdefault.jpg",
    "duration": "00:55",
    "position": 2
  },
  {
    "id": "3",
    "videoId": "uFpBCC2Qpj0",
    "title": "Resep Healthy Snacking - Surabi Sultan Banyumas",
    "thumbnail": "https://i.ytimg.com/vi/uFpBCC2Qpj0/mqdefault.jpg",
    "duration": "01:56",
    "position": 3
  },
  {
    "id": "4",
    "videoId": "IiZXDsRe-wo",
    "title": "Resep Healthy Snacking - Sop Buah Shake",
    "thumbnail": "https://i.ytimg.com/vi/IiZXDsRe-wo/mqdefault.jpg",
    "duration": "00:49",
    "position": 4
  },
  {
    "id": "5",
    "videoId": "NJ_c5vtAKXA",
    "title": "Resep Healthy Snacking - Coconut Tart",
    "thumbnail": "https://i.ytimg.com/vi/NJ_c5vtAKXA/mqdefault.jpg",
    "duration": "01:43",
    "position": 5
  }
]